cbthelper/AutomatedTest.py
cbthelper/CapsBuilder.py
cbthelper/Snapshot.py
cbthelper/TestHistoryBuilder.py
cbthelper/Video.py
cbthelper/__init__.py
cbthelper/globals.py
cbthelper-0.1.3.dist-info/METADATA
cbthelper-0.1.3.dist-info/RECORD
cbthelper-0.1.3.dist-info/WHEEL
cbthelper-0.1.3.dist-info/top_level.txt
