Metadata-Version: 2.1
Name: cbthelper
Version: 0.1.3
Summary: a helper library for cross browser testing's selenium api
Home-page: https://github.com/crossbrowsertesting/cbthelper-python
Author: Tim Hamilton
Author-email: timh@crossbrowsertesting.com
License: UNKNOWN
Platform: UNKNOWN
Classifier: Programming Language :: Python :: 3
Classifier: License :: OSI Approved :: MIT License
Classifier: Operating System :: OS Independent
